{"type":"Topology","arcs":[[[1511,1159],[47,-113],[0,-45],[-33,-62],[-48,-24],[75,-149],[63,-72],[-33,-32],[-63,5],[-108,-18],[-36,-54]],[[1375,595],[18,151],[-2,107],[-26,34],[-30,120],[-43,40],[18,76],[-59,85],[-43,28]],[[1208,1236],[119,11],[32,35]],[[1359,1282],[37,-15],[27,-62],[71,-11],[17,-35]],[[1146,1609],[45,-75],[12,-103],[35,-66],[121,-83]],[[1208,1236],[-97,18],[-19,-26],[14,-119]],[[1106,1109],[-32,10],[-113,-33],[-50,-27]],[[911,1059],[-11,65],[-58,13],[2,37],[77,44],[34,44],[56,39],[-46,110],[-54,10],[-88,-34],[-20,35],[-92,-4],[-26,10]],[[685,1428],[-18,82],[-82,80],[-60,-14],[-95,75],[-25,36],[-86,-11],[-57,42]],[[262,1718],[38,65],[147,-6],[43,40]],[[490,1817],[48,-10],[29,-33],[40,-94],[59,-4],[102,29],[64,-48],[63,-64],[251,16]],[[1106,1109],[18,-38],[52,-49],[3,-94],[-43,-41],[41,-73],[-19,-145],[-62,-61],[-38,-76],[7,-49],[-22,-69],[-27,-27],[-5,-61],[-24,-62]],[[987,264],[-85,58],[-78,-59],[-51,32],[-76,-26],[-117,31],[-64,-45],[-86,-6],[-31,14],[-51,-21],[-68,27],[-60,110],[-6,55],[-99,40],[3,37],[36,43]],[[154,554],[46,36],[83,25],[118,14],[19,-9],[117,40],[35,-20],[90,70],[-7,37],[24,142],[61,47],[51,-1],[83,44],[37,80]],[[3044,2015],[-50,10],[-51,-17],[-89,-121],[-94,-56],[-139,-30],[-34,-53],[-92,-26],[-33,6],[-33,47],[-46,12],[-62,-32],[-24,-46],[-53,-36]],[[2244,1673],[-24,52],[34,87],[23,120],[44,56],[18,90],[-20,60],[24,56],[-11,56],[56,50],[112,35]],[[2500,2335],[50,-31],[120,23],[53,-51],[50,34],[25,-13],[49,-67],[172,-77],[50,-71],[-25,-67]],[[2244,1673],[-59,-8],[-33,34],[-41,10],[-36,-21]],[[2075,1688],[-72,56],[-47,15],[-26,42],[2,45]],[[1932,1846],[21,8],[11,99],[-20,39],[-8,73],[57,82],[-9,30],[41,67],[75,87],[5,100],[-15,36],[25,28],[89,17],[34,26],[29,-32],[58,-12],[50,-60],[97,-56],[28,-43]],[[2303,1107],[-36,-50]],[[2267,1057],[-64,-11],[-73,-53],[-55,-9],[-51,-46],[-1,-39],[-33,-53],[6,-81],[-43,-57],[12,-70],[-13,-106],[22,-36],[-48,-160],[-86,-91],[-31,-59],[-14,-2],[-62,40],[-44,-12],[-48,69],[-136,-10],[-121,58]],[[1384,329],[0,62],[-44,80],[3,45],[32,79]],[[1511,1159],[73,45],[77,-16],[46,5],[40,59],[108,84],[89,-47],[34,-49],[69,-60],[80,16],[-6,117],[62,154]],[[2183,1467],[54,-44],[25,-44],[-47,-127],[30,-69],[58,-76]],[[911,1059],[-52,25],[-174,-21],[-117,35],[-49,26],[-7,75],[-68,40],[105,53],[18,110],[103,8],[15,18]],[[2075,1688],[15,-43],[57,-61],[31,-12],[29,-97],[-24,-8]],[[1146,1609],[-4,58],[-59,50]],[[1083,1717],[58,33],[21,88],[66,50],[124,-20],[67,-53],[100,-46],[53,16],[46,47],[77,12],[26,28],[103,-32],[108,6]],[[490,1817],[3,52],[49,86],[96,-54],[29,-46],[112,-48],[28,-53],[57,-15],[27,17],[95,-11],[97,-28]],[[3044,2015],[27,-57],[-7,-29],[69,-29],[-13,-82],[-49,-28],[-8,-38]],[[3063,1752],[-89,20],[-112,-16],[-31,-33],[-54,-8],[-26,28],[-110,-5],[-52,-65],[-75,-159],[-102,-87],[-12,-72],[-37,-44],[-16,-61],[-5,-83],[-39,-60]],[[154,554],[-48,18],[-18,59],[-7,101],[-57,34],[-24,116],[39,144],[58,47],[9,37],[46,34],[-46,144],[10,65],[24,38],[-4,40],[-42,51],[-4,110],[59,70],[106,42],[7,14]],[[3063,1752],[7,-43],[-34,-69],[-36,-16],[-54,-58],[-66,10],[-66,-25],[-28,-36],[-20,-108],[-70,-83],[-101,-61],[-11,-102],[-19,-17],[-76,0],[-64,-79],[-51,-29],[-107,21]],[[1384,329],[-131,-72],[-33,-63],[-35,-112],[3,-31],[-64,-51],[-53,27],[-8,112],[-39,22],[2,40],[-39,63]]],"transform":{"scale":[0.0002296312240689182,0.0002199904453091863],"translate":[-79.33161861330831,-7.251489974982292]},"objects":{"cajamarca_san_miguel_distritos":{"type":"GeometryCollection","geometries":[{"arcs":[[0,1,2,3]],"type":"Polygon","properties":{"CCDD":"06","NOMBDEP":"CAJAMARCA","CCPP":"11","NOMBPROV":"SAN MIGUEL","CCDI":"05","NOMBDIST":"EL PRADO","CAPITAL":"EL PRADO","UBIGEO":"061105","IDPROV":"0611","CODIGO":"061105","CNT_CCPP":15,"DESCRIPCIO":"EL PRADO","name":"061105","departamento":"CAJAMARCA","provincia":"SAN MIGUEL","distrito":"EL PRADO","ubigeo_inei":"061105","ubigeo_provincia":"0611"}},{"arcs":[[4,-3,5,6,7,8,9,10]],"type":"Polygon","properties":{"CCDD":"06","NOMBDEP":"CAJAMARCA","CCPP":"11","NOMBPROV":"SAN MIGUEL","CCDI":"09","NOMBDIST":"NIEPOS","CAPITAL":"NIEPOS","UBIGEO":"061109","IDPROV":"0611","CODIGO":"061109","CNT_CCPP":41,"DESCRIPCIO":"NIEPOS","name":"061109","departamento":"CAJAMARCA","provincia":"SAN MIGUEL","distrito":"NIEPOS","ubigeo_inei":"061109","ubigeo_provincia":"0611"}},{"arcs":[[11,12,13,-7]],"type":"Polygon","properties":{"CCDD":"06","NOMBDEP":"CAJAMARCA","CCPP":"11","NOMBPROV":"SAN MIGUEL","CCDI":"10","NOMBDIST":"SAN GREGORIO","CAPITAL":"SAN GREGORIO","UBIGEO":"061110","IDPROV":"0611","CODIGO":"061110","CNT_CCPP":48,"DESCRIPCIO":"SAN GREGORIO","name":"061110","departamento":"CAJAMARCA","provincia":"SAN MIGUEL","distrito":"SAN GREGORIO","ubigeo_inei":"061110","ubigeo_provincia":"0611"}},{"arcs":[[14,15,16]],"type":"Polygon","properties":{"CCDD":"06","NOMBDEP":"CAJAMARCA","CCPP":"11","NOMBPROV":"SAN MIGUEL","CCDI":"04","NOMBDIST":"CATILLUC","CAPITAL":"CATILLUC","UBIGEO":"061104","IDPROV":"0611","CODIGO":"061104","CNT_CCPP":23,"DESCRIPCIO":"CATILLUC","name":"061104","departamento":"CAJAMARCA","provincia":"SAN MIGUEL","distrito":"CATILLUC","ubigeo_inei":"061104","ubigeo_provincia":"0611"}},{"arcs":[[-16,17,18,19]],"type":"Polygon","properties":{"CCDD":"06","NOMBDEP":"CAJAMARCA","CCPP":"11","NOMBPROV":"SAN MIGUEL","CCDI":"12","NOMBDIST":"TONGOD","CAPITAL":"TONGOD","UBIGEO":"061112","IDPROV":"0611","CODIGO":"061112","CNT_CCPP":24,"DESCRIPCIO":"TONGOD","name":"061112","departamento":"CAJAMARCA","provincia":"SAN MIGUEL","distrito":"TONGOD","ubigeo_inei":"061112","ubigeo_provincia":"0611"}},{"arcs":[[20,21,22,-1,23,24]],"type":"Polygon","properties":{"CCDD":"06","NOMBDEP":"CAJAMARCA","CCPP":"11","NOMBPROV":"SAN MIGUEL","CCDI":"01","NOMBDIST":"SAN MIGUEL","CAPITAL":"SAN MIGUEL DE PALLAQUES","UBIGEO":"061101","IDPROV":"0611","CODIGO":"061101","CNT_CCPP":68,"DESCRIPCIO":"SAN MIGUEL","name":"061101","departamento":"CAJAMARCA","provincia":"SAN MIGUEL","distrito":"SAN MIGUEL","ubigeo_inei":"061101","ubigeo_provincia":"0611"}},{"arcs":[[25,-8]],"type":"Polygon","properties":{"CCDD":"06","NOMBDEP":"CAJAMARCA","CCPP":"11","NOMBPROV":"SAN MIGUEL","CCDI":"02","NOMBDIST":"BOLIVAR","CAPITAL":"BOLIVAR","UBIGEO":"061102","IDPROV":"0611","CODIGO":"061102","CNT_CCPP":30,"DESCRIPCIO":"BOLIVAR","name":"061102","departamento":"CAJAMARCA","provincia":"SAN MIGUEL","distrito":"BOLIVAR","ubigeo_inei":"061102","ubigeo_provincia":"0611"}},{"arcs":[[-19,26,-24,-4,-5,27,28]],"type":"Polygon","properties":{"CCDD":"06","NOMBDEP":"CAJAMARCA","CCPP":"11","NOMBPROV":"SAN MIGUEL","CCDI":"03","NOMBDIST":"CALQUIS","CAPITAL":"CALQUIS","UBIGEO":"061103","IDPROV":"0611","CODIGO":"061103","CNT_CCPP":24,"DESCRIPCIO":"CALQUIS","name":"061103","departamento":"CAJAMARCA","provincia":"SAN MIGUEL","distrito":"CALQUIS","ubigeo_inei":"061103","ubigeo_provincia":"0611"}},{"arcs":[[-28,-11,29]],"type":"Polygon","properties":{"CCDD":"06","NOMBDEP":"CAJAMARCA","CCPP":"11","NOMBPROV":"SAN MIGUEL","CCDI":"06","NOMBDIST":"LA FLORIDA","CAPITAL":"LA FLORIDA","UBIGEO":"061106","IDPROV":"0611","CODIGO":"061106","CNT_CCPP":28,"DESCRIPCIO":"LA FLORIDA","name":"061106","departamento":"CAJAMARCA","provincia":"SAN MIGUEL","distrito":"LA FLORIDA","ubigeo_inei":"061106","ubigeo_provincia":"0611"}},{"arcs":[[30,31,-25,-27,-18,-15]],"type":"Polygon","properties":{"CCDD":"06","NOMBDEP":"CAJAMARCA","CCPP":"11","NOMBPROV":"SAN MIGUEL","CCDI":"07","NOMBDIST":"LLAPA","CAPITAL":"LLAPA","UBIGEO":"061107","IDPROV":"0611","CODIGO":"061107","CNT_CCPP":27,"DESCRIPCIO":"LLAPA","name":"061107","departamento":"CAJAMARCA","provincia":"SAN MIGUEL","distrito":"LLAPA","ubigeo_inei":"061107","ubigeo_provincia":"0611"}},{"arcs":[[-26,-14,32,-9]],"type":"Polygon","properties":{"CCDD":"06","NOMBDEP":"CAJAMARCA","CCPP":"11","NOMBPROV":"SAN MIGUEL","CCDI":"08","NOMBDIST":"NANCHOC","CAPITAL":"NANCHOC","UBIGEO":"061108","IDPROV":"0611","CODIGO":"061108","CNT_CCPP":39,"DESCRIPCIO":"NANCHOC","name":"061108","departamento":"CAJAMARCA","provincia":"SAN MIGUEL","distrito":"NANCHOC","ubigeo_inei":"061108","ubigeo_provincia":"0611"}},{"arcs":[[33,-21,-32]],"type":"Polygon","properties":{"CCDD":"06","NOMBDEP":"CAJAMARCA","CCPP":"11","NOMBPROV":"SAN MIGUEL","CCDI":"11","NOMBDIST":"SAN SILVESTRE DE COCHAN","CAPITAL":"SAN SILVESTRE DE COCHAN","UBIGEO":"061111","IDPROV":"0611","CODIGO":"061111","CNT_CCPP":34,"DESCRIPCIO":"SAN SILVESTRE DE COCHAN","name":"061111","departamento":"CAJAMARCA","provincia":"SAN MIGUEL","distrito":"SAN SILVESTRE DE COCHAN","ubigeo_inei":"061111","ubigeo_provincia":"0611"}},{"arcs":[[-2,-23,34,-12,-6]],"type":"Polygon","properties":{"CCDD":"06","NOMBDEP":"CAJAMARCA","CCPP":"11","NOMBPROV":"SAN MIGUEL","CCDI":"13","NOMBDIST":"UNION AGUA BLANCA","CAPITAL":"AGUA BLANCA","UBIGEO":"061113","IDPROV":"0611","CODIGO":"061113","CNT_CCPP":32,"DESCRIPCIO":"UNION AGUA BLANCA","name":"061113","departamento":"CAJAMARCA","provincia":"SAN MIGUEL","distrito":"UNION AGUA BLANCA","ubigeo_inei":"061113","ubigeo_provincia":"0611"}}]}}}